lib_api_client/__init__.py
lib_api_client/client.py
lib_api_client/const.py
lib_api_client/exception.py
lib_api_client/session_pool.py
lib_api_client/utils.py
libapiclient-0.0.3.dist-info/LICENSE
libapiclient-0.0.3.dist-info/METADATA
libapiclient-0.0.3.dist-info/WHEEL
libapiclient-0.0.3.dist-info/top_level.txt
libapiclient-0.0.3.dist-info/RECORD
